cp2k_output_tools/__init__.py
cp2k_output_tools/bandstructure_parser.py
cp2k_output_tools/blocks/__init__.py
cp2k_output_tools/blocks/bibliography.py
cp2k_output_tools/blocks/common.py
cp2k_output_tools/blocks/condition_number.py
cp2k_output_tools/blocks/energies.py
cp2k_output_tools/blocks/forces.py
cp2k_output_tools/blocks/kv_sections.py
cp2k_output_tools/blocks/mulliken.py
cp2k_output_tools/blocks/program_info.py
cp2k_output_tools/blocks/warnings.py
cp2k_output_tools/cli.py
cp2k_output_tools/parser.py
cp2k_output_tools/scripts/pdos.py
cp2k_output_tools/trajectories/xyz.py
cp2k_output_tools/trajectories/xyz_cli.py
cp2k_output_tools-0.5.0.dist-info/entry_points.txt
cp2k_output_tools-0.5.0.dist-info/WHEEL
cp2k_output_tools-0.5.0.dist-info/METADATA
cp2k_output_tools-0.5.0.dist-info/RECORD
