Metadata-Version: 2.1
Name: cp2k-output-tools
Version: 0.5.0
Summary: Python tools to handle CP2K output files
Home-page: https://github.com/cp2k/cp2k-output-tools
License: MIT
Author: Tiziano Müller
Author-email: tiziano.mueller@chem.uzh.ch
Requires-Python: >=3.6,<4.0
Classifier: Development Status :: 4 - Beta
Classifier: Environment :: Console
Classifier: Intended Audience :: Science/Research
Classifier: License :: OSI Approved :: MIT License
Classifier: Operating System :: OS Independent
Classifier: Programming Language :: Python :: 3
Classifier: Programming Language :: Python :: 3.6
Classifier: Programming Language :: Python :: 3.7
Classifier: Programming Language :: Python :: 3.8
Classifier: Programming Language :: Python :: 3.9
Classifier: Topic :: Scientific/Engineering :: Chemistry
Classifier: Topic :: Software Development :: Libraries :: Python Modules
Provides-Extra: yaml
Requires-Dist: click (>=8.0.1,<9.0.0)
Requires-Dist: dataclasses (>=0.7,<1); python_version >= "3.6" and python_version < "3.7"
Requires-Dist: numpy (>=1.19,<2.0)
Requires-Dist: regex (>=2021.4,<2022.0)
Requires-Dist: ruamel.yaml (>=0.16.5,<0.18.0); extra == "yaml"
Project-URL: Repository, https://github.com/cp2k/cp2k-output-tools
